perg_search-0.0.2.dist-info/licenses/LICENSE
syntaxes/__init__.py
syntaxes/bash.py
syntaxes/general.py
syntaxes/python.py
perg_search-0.0.2.dist-info/METADATA
perg_search-0.0.2.dist-info/WHEEL
perg_search-0.0.2.dist-info/entry_points.txt
perg_search-0.0.2.dist-info/top_level.txt
perg_search-0.0.2.dist-info/RECORD
