Metadata-Version: 2.4
Name: perg-search
Version: 0.0.2
Summary: Search code for patterns that match a given string
Author-email: Evan Krall <evan@evankrall.com>
License-Expression: MIT
Requires-Python: >=3.9
License-File: LICENSE
Requires-Dist: tree-sitter
Requires-Dist: tree-sitter-python
Requires-Dist: tree-sitter-bash
Dynamic: license-file
